balans/__init__.py
balans/_version.py
balans/base_instance.py
balans/base_mip.py
balans/base_state.py
balans/solver.py
balans/solver_gurobi.py
balans/solver_scip.py
balans/utils.py
balans/destroy/__init__.py
balans/destroy/crossover.py
balans/destroy/dins.py
balans/destroy/local_branching.py
balans/destroy/local_branching_relax.py
balans/destroy/mutation.py
balans/destroy/proximity.py
balans/destroy/random_objective.py
balans/destroy/rens.py
balans/destroy/rins.py
balans/repair/__init__.py
balans/repair/repair.py
balans-1.0.1.dist-info/LICENSE
balans-1.0.1.dist-info/METADATA
balans-1.0.1.dist-info/WHEEL
balans-1.0.1.dist-info/top_level.txt
balans-1.0.1.dist-info/RECORD
