Metadata-Version: 2.1
Name: balans
Version: 1.0.1
Summary: Balans: Bandit-based Adaptive Large Neighborhood Search
Home-page: https://github.com/skadio/balns
Author: skadio
Project-URL: Documentation, https://github.com/skadio/balans
Project-URL: Source, https://github.com/skadio/balans
Classifier: License :: OSI Approved :: Apache Software License
Classifier: Programming Language :: Python :: 3.8
Classifier: Operating System :: OS Independent
License-File: LICENSE
